MANIFEST.in
README.rst
setup.py
docs/HISTORY.rst
docs/INSTALL.txt
docs/LICENSE.GPL
docs/LICENSE.txt
redturtle/__init__.py
redturtle.custommenu.factories.egg-info/PKG-INFO
redturtle.custommenu.factories.egg-info/SOURCES.txt
redturtle.custommenu.factories.egg-info/dependency_links.txt
redturtle.custommenu.factories.egg-info/entry_points.txt
redturtle.custommenu.factories.egg-info/namespace_packages.txt
redturtle.custommenu.factories.egg-info/not-zip-safe
redturtle.custommenu.factories.egg-info/requires.txt
redturtle.custommenu.factories.egg-info/top_level.txt
redturtle/custommenu/__init__.py
redturtle/custommenu/factories/README.txt
redturtle/custommenu/factories/__init__.py
redturtle/custommenu/factories/config.py
redturtle/custommenu/factories/configure.zcml
redturtle/custommenu/factories/interfaces.py
redturtle/custommenu/factories/menu.py
redturtle/custommenu/factories/overrides.zcml
redturtle/custommenu/factories/profiles.zcml
redturtle/custommenu/factories/Extensions/__init__.py
redturtle/custommenu/factories/Extensions/install.py
redturtle/custommenu/factories/adapters/__init__.py
redturtle/custommenu/factories/adapters/adapters.py
redturtle/custommenu/factories/adapters/configure.zcml
redturtle/custommenu/factories/browser/__init__.py
redturtle/custommenu/factories/browser/configure.zcml
redturtle/custommenu/factories/browser/enabled.pt
redturtle/custommenu/factories/browser/rt_manageform.css
redturtle/custommenu/factories/browser/rt_manageform.js
redturtle/custommenu/factories/browser/view.pt
redturtle/custommenu/factories/browser/view.py
redturtle/custommenu/factories/exportimport/__init__.py
redturtle/custommenu/factories/exportimport/configure.zcml
redturtle/custommenu/factories/exportimport/handlers.py
redturtle/custommenu/factories/exportimport/interfaces.py
redturtle/custommenu/factories/locales/rebuildPo.sh
redturtle/custommenu/factories/locales/redturtle.custommenu.factories-manual.pot
redturtle/custommenu/factories/locales/redturtle.custommenu.factories.pot
redturtle/custommenu/factories/locales/it/LC_MESSAGES/redturtle.custommenu.factories.mo
redturtle/custommenu/factories/locales/it/LC_MESSAGES/redturtle.custommenu.factories.po
redturtle/custommenu/factories/profiles/default/browserlayer.xml
redturtle/custommenu/factories/profiles/default/cssregistry.xml
redturtle/custommenu/factories/profiles/default/jsregistry.xml
redturtle/custommenu/factories/profiles/default/metadata.xml
