Metadata-Version: 1.0
Name: redturtle.custommenu.factories
Version: 0.3.1
Summary: Customize the Plone "add portal content" menu
Home-page: http://plone.org/products/redturtle.custommenu.factories
Author: keul
Author-email: luca@keul.it
License: GPL
Keywords: plone menu factories customize
Platform: UNKNOWN
Classifier: Framework :: Plone
Classifier: Framework :: Plone :: 3.3
Classifier: Framework :: Plone :: 4.0
Classifier: Framework :: Plone :: 4.1
Classifier: Framework :: Plone :: 4.2
Classifier: Framework :: Plone :: 4.3
Classifier: Programming Language :: Python
Classifier: Development Status :: 5 - Production/Stable
